{
  "formatVersion": 1,
  "database": {
    "version": 16,
    "identityHash": "78096838089059af7d0362603fe38880",
    "entities": [
      {
        "tableName": "webapps",
        "createSql": "CREATE TABLE IF NOT EXISTS `${TABLE_NAME}` (`uuid` TEXT NOT NULL, `baseUrl` TEXT NOT NULL, `title` TEXT NOT NULL, `isUseContainer` INTEGER NOT NULL, `isEphemeralSandbox` INTEGER NOT NULL, `order` INTEGER NOT NULL, `groupUuid` TEXT, `isOpenUrlExternal` INTEGER, `isAllowJs` INTEGER, `isRequestDesktop` INTEGER, `isClearCache` INTEGER, `isAlwaysHttps` INTEGER, `isAllowLocationAccess` INTEGER, `customHeaders` TEXT, `isAutoReload` INTEGER, `timeAutoReload` INTEGER, `colorScheme` INTEGER, `isDrmAllowed` INTEGER, `isShowFullscreen` INTEGER, `isKeepAwake` INTEGER, `isCameraPermission` INTEGER, `isMicrophonePermission` INTEGER, `isBiometricProtection` INTEGER, `isAllowMediaPlaybackInBackground` INTEGER, `isLongClickShare` INTEGER, `isShowProgressbar` INTEGER, `isDisableScreenshots` INTEGER, `isPullToRefresh` INTEGER, `isSafeBrowsing` INTEGER, `isDynamicStatusBar` INTEGER, `isShowNotification` INTEGER, `isAppLinksPermission` INTEGER, `isGlobalPrivacyControl` INTEGER, `isFingerprintingProtection` INTEGER, `isBlockLocalNetwork` INTEGER, `isBlockWebRtcIpLeak` INTEGER, `isUseBasicAuth` INTEGER, `basicAuthUsername` TEXT, `basicAuthPassword` TEXT, PRIMARY KEY(`uuid`))",
        "fields": [
          {
            "fieldPath": "uuid",
            "columnName": "uuid",
            "affinity": "TEXT",
            "notNull": true
          },
          {
            "fieldPath": "baseUrl",
            "columnName": "baseUrl",
            "affinity": "TEXT",
            "notNull": true
          },
          {
            "fieldPath": "title",
            "columnName": "title",
            "affinity": "TEXT",
            "notNull": true
          },
          {
            "fieldPath": "isUseContainer",
            "columnName": "isUseContainer",
            "affinity": "INTEGER",
            "notNull": true
          },
          {
            "fieldPath": "isEphemeralSandbox",
            "columnName": "isEphemeralSandbox",
            "affinity": "INTEGER",
            "notNull": true
          },
          {
            "fieldPath": "order",
            "columnName": "order",
            "affinity": "INTEGER",
            "notNull": true
          },
          {
            "fieldPath": "groupUuid",
            "columnName": "groupUuid",
            "affinity": "TEXT"
          },
          {
            "fieldPath": "settings.isOpenUrlExternal",
            "columnName": "isOpenUrlExternal",
            "affinity": "INTEGER"
          },
          {
            "fieldPath": "settings.isAllowJs",
            "columnName": "isAllowJs",
            "affinity": "INTEGER"
          },
          {
            "fieldPath": "settings.isRequestDesktop",
            "columnName": "isRequestDesktop",
            "affinity": "INTEGER"
          },
          {
            "fieldPath": "settings.isClearCache",
            "columnName": "isClearCache",
            "affinity": "INTEGER"
          },
          {
            "fieldPath": "settings.isAlwaysHttps",
            "columnName": "isAlwaysHttps",
            "affinity": "INTEGER"
          },
          {
            "fieldPath": "settings.isAllowLocationAccess",
            "columnName": "isAllowLocationAccess",
            "affinity": "INTEGER"
          },
          {
            "fieldPath": "settings.customHeaders",
            "columnName": "customHeaders",
            "affinity": "TEXT"
          },
          {
            "fieldPath": "settings.isAutoReload",
            "columnName": "isAutoReload",
            "affinity": "INTEGER"
          },
          {
            "fieldPath": "settings.timeAutoReload",
            "columnName": "timeAutoReload",
            "affinity": "INTEGER"
          },
          {
            "fieldPath": "settings.colorScheme",
            "columnName": "colorScheme",
            "affinity": "INTEGER"
          },
          {
            "fieldPath": "settings.isDrmAllowed",
            "columnName": "isDrmAllowed",
            "affinity": "INTEGER"
          },
          {
            "fieldPath": "settings.isShowFullscreen",
            "columnName": "isShowFullscreen",
            "affinity": "INTEGER"
          },
          {
            "fieldPath": "settings.isKeepAwake",
            "columnName": "isKeepAwake",
            "affinity": "INTEGER"
          },
          {
            "fieldPath": "settings.isCameraPermission",
            "columnName": "isCameraPermission",
            "affinity": "INTEGER"
          },
          {
            "fieldPath": "settings.isMicrophonePermission",
            "columnName": "isMicrophonePermission",
            "affinity": "INTEGER"
          },
          {
            "fieldPath": "settings.isBiometricProtection",
            "columnName": "isBiometricProtection",
            "affinity": "INTEGER"
          },
          {
            "fieldPath": "settings.isAllowMediaPlaybackInBackground",
            "columnName": "isAllowMediaPlaybackInBackground",
            "affinity": "INTEGER"
          },
          {
            "fieldPath": "settings.isLongClickShare",
            "columnName": "isLongClickShare",
            "affinity": "INTEGER"
          },
          {
            "fieldPath": "settings.isShowProgressbar",
            "columnName": "isShowProgressbar",
            "affinity": "INTEGER"
          },
          {
            "fieldPath": "settings.isDisableScreenshots",
            "columnName": "isDisableScreenshots",
            "affinity": "INTEGER"
          },
          {
            "fieldPath": "settings.isPullToRefresh",
            "columnName": "isPullToRefresh",
            "affinity": "INTEGER"
          },
          {
            "fieldPath": "settings.isSafeBrowsing",
            "columnName": "isSafeBrowsing",
            "affinity": "INTEGER"
          },
          {
            "fieldPath": "settings.isDynamicStatusBar",
            "columnName": "isDynamicStatusBar",
            "affinity": "INTEGER"
          },
          {
            "fieldPath": "settings.isShowNotification",
            "columnName": "isShowNotification",
            "affinity": "INTEGER"
          },
          {
            "fieldPath": "settings.isAppLinksPermission",
            "columnName": "isAppLinksPermission",
            "affinity": "INTEGER"
          },
          {
            "fieldPath": "settings.isGlobalPrivacyControl",
            "columnName": "isGlobalPrivacyControl",
            "affinity": "INTEGER"
          },
          {
            "fieldPath": "settings.isFingerprintingProtection",
            "columnName": "isFingerprintingProtection",
            "affinity": "INTEGER"
          },
          {
            "fieldPath": "settings.isBlockLocalNetwork",
            "columnName": "isBlockLocalNetwork",
            "affinity": "INTEGER"
          },
          {
            "fieldPath": "settings.isBlockWebRtcIpLeak",
            "columnName": "isBlockWebRtcIpLeak",
            "affinity": "INTEGER"
          },
          {
            "fieldPath": "settings.isUseBasicAuth",
            "columnName": "isUseBasicAuth",
            "affinity": "INTEGER"
          },
          {
            "fieldPath": "settings.basicAuthUsername",
            "columnName": "basicAuthUsername",
            "affinity": "TEXT"
          },
          {
            "fieldPath": "settings.basicAuthPassword",
            "columnName": "basicAuthPassword",
            "affinity": "TEXT"
          }
        ],
        "primaryKey": {
          "autoGenerate": false,
          "columnNames": [
            "uuid"
          ]
        }
      },
      {
        "tableName": "webapp_groups",
        "createSql": "CREATE TABLE IF NOT EXISTS `${TABLE_NAME}` (`uuid` TEXT NOT NULL, `title` TEXT NOT NULL, `order` INTEGER NOT NULL, `isUseContainer` INTEGER NOT NULL, `isEphemeralSandbox` INTEGER NOT NULL, `isOpenUrlExternal` INTEGER, `isAllowJs` INTEGER, `isRequestDesktop` INTEGER, `isClearCache` INTEGER, `isAlwaysHttps` INTEGER, `isAllowLocationAccess` INTEGER, `customHeaders` TEXT, `isAutoReload` INTEGER, `timeAutoReload` INTEGER, `colorScheme` INTEGER, `isDrmAllowed` INTEGER, `isShowFullscreen` INTEGER, `isKeepAwake` INTEGER, `isCameraPermission` INTEGER, `isMicrophonePermission` INTEGER, `isBiometricProtection` INTEGER, `isAllowMediaPlaybackInBackground` INTEGER, `isLongClickShare` INTEGER, `isShowProgressbar` INTEGER, `isDisableScreenshots` INTEGER, `isPullToRefresh` INTEGER, `isSafeBrowsing` INTEGER, `isDynamicStatusBar` INTEGER, `isShowNotification` INTEGER, `isAppLinksPermission` INTEGER, `isGlobalPrivacyControl` INTEGER, `isFingerprintingProtection` INTEGER, `isBlockLocalNetwork` INTEGER, `isBlockWebRtcIpLeak` INTEGER, `isUseBasicAuth` INTEGER, `basicAuthUsername` TEXT, `basicAuthPassword` TEXT, PRIMARY KEY(`uuid`))",
        "fields": [
          {
            "fieldPath": "uuid",
            "columnName": "uuid",
            "affinity": "TEXT",
            "notNull": true
          },
          {
            "fieldPath": "title",
            "columnName": "title",
            "affinity": "TEXT",
            "notNull": true
          },
          {
            "fieldPath": "order",
            "columnName": "order",
            "affinity": "INTEGER",
            "notNull": true
          },
          {
            "fieldPath": "isUseContainer",
            "columnName": "isUseContainer",
            "affinity": "INTEGER",
            "notNull": true
          },
          {
            "fieldPath": "isEphemeralSandbox",
            "columnName": "isEphemeralSandbox",
            "affinity": "INTEGER",
            "notNull": true
          },
          {
            "fieldPath": "settings.isOpenUrlExternal",
            "columnName": "isOpenUrlExternal",
            "affinity": "INTEGER"
          },
          {
            "fieldPath": "settings.isAllowJs",
            "columnName": "isAllowJs",
            "affinity": "INTEGER"
          },
          {
            "fieldPath": "settings.isRequestDesktop",
            "columnName": "isRequestDesktop",
            "affinity": "INTEGER"
          },
          {
            "fieldPath": "settings.isClearCache",
            "columnName": "isClearCache",
            "affinity": "INTEGER"
          },
          {
            "fieldPath": "settings.isAlwaysHttps",
            "columnName": "isAlwaysHttps",
            "affinity": "INTEGER"
          },
          {
            "fieldPath": "settings.isAllowLocationAccess",
            "columnName": "isAllowLocationAccess",
            "affinity": "INTEGER"
          },
          {
            "fieldPath": "settings.customHeaders",
            "columnName": "customHeaders",
            "affinity": "TEXT"
          },
          {
            "fieldPath": "settings.isAutoReload",
            "columnName": "isAutoReload",
            "affinity": "INTEGER"
          },
          {
            "fieldPath": "settings.timeAutoReload",
            "columnName": "timeAutoReload",
            "affinity": "INTEGER"
          },
          {
            "fieldPath": "settings.colorScheme",
            "columnName": "colorScheme",
            "affinity": "INTEGER"
          },
          {
            "fieldPath": "settings.isDrmAllowed",
            "columnName": "isDrmAllowed",
            "affinity": "INTEGER"
          },
          {
            "fieldPath": "settings.isShowFullscreen",
            "columnName": "isShowFullscreen",
            "affinity": "INTEGER"
          },
          {
            "fieldPath": "settings.isKeepAwake",
            "columnName": "isKeepAwake",
            "affinity": "INTEGER"
          },
          {
            "fieldPath": "settings.isCameraPermission",
            "columnName": "isCameraPermission",
            "affinity": "INTEGER"
          },
          {
            "fieldPath": "settings.isMicrophonePermission",
            "columnName": "isMicrophonePermission",
            "affinity": "INTEGER"
          },
          {
            "fieldPath": "settings.isBiometricProtection",
            "columnName": "isBiometricProtection",
            "affinity": "INTEGER"
          },
          {
            "fieldPath": "settings.isAllowMediaPlaybackInBackground",
            "columnName": "isAllowMediaPlaybackInBackground",
            "affinity": "INTEGER"
          },
          {
            "fieldPath": "settings.isLongClickShare",
            "columnName": "isLongClickShare",
            "affinity": "INTEGER"
          },
          {
            "fieldPath": "settings.isShowProgressbar",
            "columnName": "isShowProgressbar",
            "affinity": "INTEGER"
          },
          {
            "fieldPath": "settings.isDisableScreenshots",
            "columnName": "isDisableScreenshots",
            "affinity": "INTEGER"
          },
          {
            "fieldPath": "settings.isPullToRefresh",
            "columnName": "isPullToRefresh",
            "affinity": "INTEGER"
          },
          {
            "fieldPath": "settings.isSafeBrowsing",
            "columnName": "isSafeBrowsing",
            "affinity": "INTEGER"
          },
          {
            "fieldPath": "settings.isDynamicStatusBar",
            "columnName": "isDynamicStatusBar",
            "affinity": "INTEGER"
          },
          {
            "fieldPath": "settings.isShowNotification",
            "columnName": "isShowNotification",
            "affinity": "INTEGER"
          },
          {
            "fieldPath": "settings.isAppLinksPermission",
            "columnName": "isAppLinksPermission",
            "affinity": "INTEGER"
          },
          {
            "fieldPath": "settings.isGlobalPrivacyControl",
            "columnName": "isGlobalPrivacyControl",
            "affinity": "INTEGER"
          },
          {
            "fieldPath": "settings.isFingerprintingProtection",
            "columnName": "isFingerprintingProtection",
            "affinity": "INTEGER"
          },
          {
            "fieldPath": "settings.isBlockLocalNetwork",
            "columnName": "isBlockLocalNetwork",
            "affinity": "INTEGER"
          },
          {
            "fieldPath": "settings.isBlockWebRtcIpLeak",
            "columnName": "isBlockWebRtcIpLeak",
            "affinity": "INTEGER"
          },
          {
            "fieldPath": "settings.isUseBasicAuth",
            "columnName": "isUseBasicAuth",
            "affinity": "INTEGER"
          },
          {
            "fieldPath": "settings.basicAuthUsername",
            "columnName": "basicAuthUsername",
            "affinity": "TEXT"
          },
          {
            "fieldPath": "settings.basicAuthPassword",
            "columnName": "basicAuthPassword",
            "affinity": "TEXT"
          }
        ],
        "primaryKey": {
          "autoGenerate": false,
          "columnNames": [
            "uuid"
          ]
        }
      }
    ],
    "setupQueries": [
      "CREATE TABLE IF NOT EXISTS room_master_table (id INTEGER PRIMARY KEY,identity_hash TEXT)",
      "INSERT OR REPLACE INTO room_master_table (id,identity_hash) VALUES(42, '78096838089059af7d0362603fe38880')"
    ]
  }
}